aduneoclientfedid/BaseServer.py
aduneoclientfedid/BasicXML.py
aduneoclientfedid/CfiForm.py
aduneoclientfedid/CmdArgs.py
aduneoclientfedid/Configuration.py
aduneoclientfedid/Context.py
aduneoclientfedid/CryptoTools.py
aduneoclientfedid/Explanation.py
aduneoclientfedid/Help.py
aduneoclientfedid/JWT.py
aduneoclientfedid/Proposition.py
aduneoclientfedid/Server.py
aduneoclientfedid/Template.py
aduneoclientfedid/WebConsole.py
aduneoclientfedid/WebConsoleHandler.py
aduneoclientfedid/WebRequest.py
aduneoclientfedid/__init__.py
aduneoclientfedid/__main__.py
aduneoclientfedid/WebModules/CASClientAdmin.py
aduneoclientfedid/WebModules/CASClientLogin.py
aduneoclientfedid/WebModules/CASClientLogout.py
aduneoclientfedid/WebModules/Clipboard.py
aduneoclientfedid/WebModules/ContinuousPage.py
aduneoclientfedid/WebModules/FlowHandler.py
aduneoclientfedid/WebModules/Home.py
aduneoclientfedid/WebModules/IdPClientAdmin.py
aduneoclientfedid/WebModules/OAuthClientAdmin.py
aduneoclientfedid/WebModules/OAuthClientLogin.py
aduneoclientfedid/WebModules/OAuthIntrospection.py
aduneoclientfedid/WebModules/OAuthRefresh.py
aduneoclientfedid/WebModules/OAuthRevocation.py
aduneoclientfedid/WebModules/OAuthSAMLtoAT.py
aduneoclientfedid/WebModules/OAuthTokenExchange.py
aduneoclientfedid/WebModules/OIDCClientAdmin.py
aduneoclientfedid/WebModules/OIDCClientAdminGuide.py
aduneoclientfedid/WebModules/OIDCClientLogin.py
aduneoclientfedid/WebModules/OIDCClientLogout.py
aduneoclientfedid/WebModules/OIDCUserinfo.py
aduneoclientfedid/WebModules/SAMLClientAdmin.py
aduneoclientfedid/WebModules/SAMLClientLogin.py
aduneoclientfedid/WebModules/SAMLClientLogout.py
aduneoclientfedid/WebModules/WebTest.py
aduneoclientfedid/WebModules/__init__.py
aduneoclientfedid/data/clientfedid-template.cnf
aduneoclientfedid/data/explanation.json
aduneoclientfedid/data/help.json
aduneoclientfedid/static/css/aduneo.css
aduneoclientfedid/static/css/dragWindow.css
aduneoclientfedid/static/html/azureadDeux.html
aduneoclientfedid-2.0.13.dist-info/licenses/LICENSE
aduneoclientfedid-2.0.13.dist-info/METADATA
aduneoclientfedid-2.0.13.dist-info/WHEEL
aduneoclientfedid-2.0.13.dist-info/entry_points.txt
aduneoclientfedid-2.0.13.dist-info/top_level.txt
aduneoclientfedid-2.0.13.dist-info/RECORD
