Metadata-Version: 2.4
Name: aduneoclientfedid
Version: 2.0.13
Summary: Identity Federation Test Client
Author-email: Aduneo <contact@aduneo.com>
License-Expression: Apache-2.0
Project-URL: homepage, https://www.aduneo.com
Project-URL: repository, https://github.com/Aduneo/aduneoclientfedid
Keywords: identity,federation,openid connect,oidc,oauth,oauth 2,saml,cas,sso
Classifier: Topic :: System :: Systems Administration :: Authentication/Directory
Requires-Python: >=3.6
License-File: LICENSE
Requires-Dist: urllib3
Requires-Dist: jwcrypto
Requires-Dist: pyopenssl
Provides-Extra: saml
Requires-Dist: xmlsec; extra == "saml"
Dynamic: license-file
